README.rst
logmod.py
setup.py
logmod.egg-info/PKG-INFO
logmod.egg-info/SOURCES.txt
logmod.egg-info/dependency_links.txt
logmod.egg-info/requires.txt
logmod.egg-info/top_level.txt