Metadata-Version: 1.1
Name: logmod
Version: 0.1
Summary: Log all calls to a module
Home-page: https://github.com/digitalmensch/logmod
Author: Tobias Ammann
Author-email: UNKNOWN
License: MIT
Download-URL: https://pypi.python.org/pypi/logmod
Keywords: logging,module,debugging
Platform: any
Classifier: Development Status :: 4 - Beta
Classifier: Intended Audience :: Developers
Classifier: License :: OSI Approved :: MIT License
Classifier: Operating System :: OS Independent
Classifier: Programming Language :: Python
Classifier: Programming Language :: Python :: 3.6
